zana/__init__.pyi
zana/common/__init__.py
zana/proxy/__init__.py
zana/types/__init__.py
zana/types/collections.py
zana/types/enums.py
zana-0.1.10.dist-info/METADATA
zana-0.1.10.dist-info/WHEEL
zana-0.1.10.dist-info/LICENSE.txt
zana-0.1.10.dist-info/RECORD
