Metadata-Version: 2.1
Name: zana
Version: 0.1.10
Summary: general utility functions and types
Home-page: https://github.com/python-zana/zana
License: MIT
Keywords: zana,toolkit
Author: David Kyalo
Author-email: davidmkyalo@gmail.com
Requires-Python: >=3.10,<4.0
Classifier: License :: OSI Approved :: MIT License
Classifier: Programming Language :: Python :: 3
Classifier: Programming Language :: Python :: 3.10
Classifier: Programming Language :: Python :: 3.11
Classifier: Programming Language :: Python :: 3.10
Classifier: Programming Language :: Python :: 3.9
Requires-Dist: attrs (>=21.4.0)
Requires-Dist: typing-extensions (>=4.4.0,<5.0.0)
Project-URL: Documentation, https://python-zana.github.io/zana
Project-URL: Repository, https://github.com/python-zana/zana
